insarlite/__init__.py
insarlite/__main__.py
insarlite/main.py
insarlite/gmtsar_gui/__init__.py
insarlite/gmtsar_gui/align_genIFGs.py
insarlite/gmtsar_gui/alignment.py
insarlite/gmtsar_gui/base2net.py
insarlite/gmtsar_gui/baselines_gen.py
insarlite/gmtsar_gui/data_dwn.py
insarlite/gmtsar_gui/dem_dwn.py
insarlite/gmtsar_gui/gacos_atm_corr.py
insarlite/gmtsar_gui/ifgs_generation.py
insarlite/gmtsar_gui/mask.py
insarlite/gmtsar_gui/masterselection.py
insarlite/gmtsar_gui/mean_corr.py
insarlite/gmtsar_gui/mergeIFGs.py
insarlite/gmtsar_gui/orbitsdownload.py
insarlite/gmtsar_gui/out_turn.py
insarlite/gmtsar_gui/out_visualize.py
insarlite/gmtsar_gui/pair_generation.py
insarlite/gmtsar_gui/ref_point.py
insarlite/gmtsar_gui/sb_inversion.py
insarlite/gmtsar_gui/sbas04.py
insarlite/gmtsar_gui/structuring.py
insarlite/gmtsar_gui/unwrap.py
insarlite/gmtsar_gui/unwrapping.py
insarlite/utils/__init__.py
insarlite/utils/config_manager.py
insarlite/utils/control_manager.py
insarlite/utils/data_handlers.py
insarlite/utils/earthdata_auth.py
insarlite/utils/file_operations.py
insarlite/utils/gmtsar_installer.py
insarlite/utils/gui_helpers.py
insarlite/utils/matplotlib_baseline_plotter.py
insarlite/utils/ui_factory.py
insarlite/utils/utils.py
insarlite-1.3.2.dist-info/licenses/LICENSE
insarlite-1.3.2.dist-info/METADATA
insarlite-1.3.2.dist-info/WHEEL
insarlite-1.3.2.dist-info/entry_points.txt
insarlite-1.3.2.dist-info/top_level.txt
insarlite-1.3.2.dist-info/RECORD
