Metadata-Version: 2.4
Name: insarlite
Version: 1.3.2
Summary: A comprehensive GUI application for GMTSAR-based InSAR processing
Author-email: Muhammad Badar Munir <mbadarmunir@gmail.com>
Maintainer-email: Muhammad Badar Munir <mbadarmunir@gmail.com>
Project-URL: Homepage, https://github.com/mbadarmunir/InSARLite
Project-URL: Documentation, https://insarlite.readthedocs.io/
Project-URL: Repository, https://github.com/mbadarmunir/InSARLite
Project-URL: Bug Tracker, https://github.com/mbadarmunir/InSARLite/issues
Project-URL: Changelog, https://github.com/mbadarmunir/InSARLite/blob/main/CHANGELOG.md
Keywords: InSAR,SAR,interferometry,GMTSAR,Sentinel-1,remote sensing,geodesy
Classifier: Development Status :: 5 - Production/Stable
Classifier: Intended Audience :: Science/Research
Classifier: Intended Audience :: Education
Classifier: Topic :: Scientific/Engineering :: GIS
Classifier: Topic :: Scientific/Engineering :: Visualization
Classifier: Programming Language :: Python :: 3
Classifier: Programming Language :: Python :: 3.8
Classifier: Programming Language :: Python :: 3.9
Classifier: Programming Language :: Python :: 3.10
Classifier: Programming Language :: Python :: 3.11
Classifier: Programming Language :: Python :: 3.12
Classifier: Operating System :: OS Independent
Requires-Python: >=3.8
License-File: LICENSE
Requires-Dist: numpy>=1.20.0
Requires-Dist: matplotlib>=3.3.0
Requires-Dist: rioxarray>=0.11.0
Requires-Dist: xarray>=0.18.0
Requires-Dist: h5netcdf>=0.11.0
Requires-Dist: tkcalendar>=1.6.0
Requires-Dist: tkintermapview>=1.20
Requires-Dist: requests>=2.25.0
Requires-Dist: beautifulsoup4>=4.9.0
Requires-Dist: pykml>=0.2.0
Requires-Dist: pandas>=1.3.0
Requires-Dist: asf_search>=6.0.0
Requires-Dist: shapely>=1.7.0
Requires-Dist: dask>=2021.6.0
Requires-Dist: numba<0.60.0,>=0.56.0
Requires-Dist: sparse<0.16.0,>=0.13.0
Requires-Dist: packaging>=20.0
Requires-Dist: Pillow>=8.0.0
Requires-Dist: scipy>=1.7.0
Requires-Dist: lxml>=4.6.0
Requires-Dist: netCDF4>=1.5.0
Requires-Dist: basemap>=1.3.0; platform_system != "Windows"
Provides-Extra: docs
Requires-Dist: sphinx>=4.0.0; extra == "docs"
Requires-Dist: sphinx-rtd-theme>=1.0.0; extra == "docs"
Requires-Dist: myst-parser>=0.18.0; extra == "docs"
Requires-Dist: nbsphinx>=0.8.0; extra == "docs"
Requires-Dist: sphinx-autodoc-typehints>=1.19.0; extra == "docs"
Requires-Dist: sphinx-copybutton>=0.5.0; extra == "docs"
Provides-Extra: dev
Requires-Dist: pytest>=7.0.0; extra == "dev"
Requires-Dist: pytest-cov>=4.0.0; extra == "dev"
Requires-Dist: black>=22.0.0; extra == "dev"
Requires-Dist: isort>=5.10.0; extra == "dev"
Requires-Dist: flake8>=5.0.0; extra == "dev"
Requires-Dist: mypy>=0.991; extra == "dev"
Requires-Dist: twine>=4.0.0; extra == "dev"
Requires-Dist: build>=0.8.0; extra == "dev"
Dynamic: license-file
